DA4RDM_RecSys_UserBased/__init__.py
DA4RDM_RecSys_UserBased/create_matrix.py
DA4RDM_RecSys_UserBased/evaluate_interest_rating.py
DA4RDM_RecSys_UserBased/evaluate_weight.py
DA4RDM_RecSys_UserBased/extract_data.py
DA4RDM_RecSys_UserBased/get_recommendation.py
DA4RDM_RecSys_UserBased/get_roles.py
DA4RDM_RecSys_UserBased/recommendation.py
DA4RDM_RecSys_UserBased/remove_outliers.py
DA4RDM_RecSys_UserBased-1.0.11.dist-info/LICENSE
DA4RDM_RecSys_UserBased-1.0.11.dist-info/METADATA
DA4RDM_RecSys_UserBased-1.0.11.dist-info/WHEEL
DA4RDM_RecSys_UserBased-1.0.11.dist-info/top_level.txt
DA4RDM_RecSys_UserBased-1.0.11.dist-info/RECORD
