Metadata-Version: 2.1
Name: DA4RDM-RecSys-UserBased
Version: 1.0.11
Summary: A package that recommends similar data collections based on the analysis of user-resource interaction patterns.
Classifier: Programming Language :: Python :: 3
Classifier: License :: OSI Approved :: MIT License
Classifier: Operating System :: OS Independent
Requires-Python: >=3.8
License-File: LICENSE
Requires-Dist: numpy
Requires-Dist: pandas
Requires-Dist: jsons
Requires-Dist: seaborn
Requires-Dist: scikit-learn
